{
    "ERROR-UNSUPPORTED-LANG": "Żądany język nie jest wspierany",
    "ERROR-RETRIEVING-USERS": "Wystąpił problem podczas pobierania użytkowników",
    "ERROR-USER-NOT-FOUND": "Użytkownik nie znaleziony w repozytorium",
    "ERROR-USER-EXISTS": "Użytkownik już znajduje się w repozytorium",
    "ERROR-CREATING-USER": "Podczas tworzenia użytkownika wystąpił błąd",
    "ERROR-UNABLE-TO-READ-PAYLOAD": "Serwer nie jest w stanie odczytać przesłanych danych",
    "ERROR-USER-UNAUTHORIZED": "Nieautoryzowany użytkownik",
    "ERROR-FORBIDDEN": "Użytkownik nie posiada wystarczajacych permisji do wykonania tej operacji",
    "ERROR-INCORRECT-IMPLEMENTATION": "Błąd wewnętrzny. Niepoprawna implementacja metody `populate`",
    "ERROR-INVALID-TOKEN": "Niepoprany token dostępowy",
    "ERROR-UPDATING-USER": "Wystąpił błąd podczas aktualizowania danych użytkownika",
    "ERROR-CREATING-PRODUCT": "Podczas tworzenia produktu wystąpił błąd",
    "ERROR-INVALID-PRODUCT-DESCRIPTION": "Niepoprawny klucz bądź wartość w opisie produktu",
    "ERROR-INVALID-PRODUCT-PRICE": "Niepoprany klucz bądź wartość w cenie produktu",
    "ERROR-PRODUCT-NOT-FOUND": "Produkt nieodnaleziony w repozytorium",
    "ERROR-UPDATING-PRODUCT": "Podczas aktualizowania danych produktu wystąpił problem",
    "ERROR-CREATING-CATEGORY": "Podczas tworzenia kategorii wystąpił błąd",
    "ERROR-CATEGORY-NOT-FOUND": "Kategoria nieodnaleziona w repozytorium",
    "ERROR-UPDATING-CATEGORY": "Podczas aktualizowania danych kategorii wystąpił błąd",
    "ERROR-COUPON-NOT-FOUND": "Kupon nieodnaleziony w repozytorium",
    "ERROR-UPDATING-COUPON": "Podczas aktualizowania danych kuponu wystąpił błąd",
    "ERROR-ORDER-NOT-FOUND": "Zamówienie nieodnalezione w repozytorium",
    "ERROR-UPDATING-ORDER": "Podczas aktualizowania zamówienia wystąpił błąd",
    "ERROR-CREATING-ORDER": "Podczas składania zamówienia wystąpił błąd",
    "ERROR-INVALID-BASKET-VALUE": "Niepoprawna wartość wewnątrz koszyka"
}